LICENSE
MANIFEST.in
README.rst
requirements.txt
setup.cfg
setup.py
rube/__init__.py
rube.fedora.egg-info/PKG-INFO
rube.fedora.egg-info/SOURCES.txt
rube.fedora.egg-info/dependency_links.txt
rube.fedora.egg-info/namespace_packages.txt
rube.fedora.egg-info/not-zip-safe
rube.fedora.egg-info/requires.txt
rube.fedora.egg-info/top_level.txt
rube/fedora/__init__.py
rube/fedora/test_askbot.py
rube/fedora/test_basepage.py
rube/fedora/test_bodhi.py
rube/fedora/test_busmon.py
rube/fedora/test_collectd.py
rube/fedora/test_docs.py
rube/fedora/test_easyfix.py
rube/fedora/test_elections.py
rube/fedora/test_fas.py
rube/fedora/test_haproxy.py
rube/fedora/test_koji.py
rube/fedora/test_nagios.py
rube/fedora/test_packages.py
rube/fedora/test_paste.py
rube/fedora/test_pkgdb.py
rube/fedora/test_pkgs.py
rube/fedora/test_wiki.py