Metadata-Version: 1.1
Name: rube.fedora
Version: 0.1.1
Summary: Rube tests for Fedora Infrastructure
Home-page: http://github.com/fedora-infra/rube/
Author: Ralph Bean
Author-email: rbean@redhat.com
License: AGPL
Platform: UNKNOWN
Classifier: Environment :: Web Environment
Classifier: Topic :: Software Development :: Libraries :: Python Modules
Classifier: Topic :: Software Development :: Quality Assurance
Classifier: Topic :: Software Development :: Testing
Classifier: Topic :: Software Development :: Testing :: Traffic Generation
Classifier: Intended Audience :: Developers
Classifier: Operating System :: OS Independent
Classifier: Programming Language :: Python
